crockode/__init__.py
crockode/crockode.py
crockode/utils.py
crockode-0.1.1.dist-info/LICENSE
crockode-0.1.1.dist-info/METADATA
crockode-0.1.1.dist-info/WHEEL
crockode-0.1.1.dist-info/RECORD
