Metadata-Version: 2.1
Name: crockode
Version: 0.1.1
Summary: A packagees into DNA, RNA or protein sequences.
License: MIT
Author: Michela Palamin, Simone Procaccia, Erin Chung, Joshua Talks
Requires-Python: >=3.9,<4.0
Classifier: License :: OSI Approved :: MIT License
Classifier: Programming Language :: Python :: 3
Classifier: Programming Language :: Python :: 3.9
Classifier: Programming Language :: Python :: 3.10
Classifier: Programming Language :: Python :: 3.11
Classifier: Programming Language :: Python :: 3.12
